tobe_time_mcp_11/__init__.py
tobe_time_mcp_11/server.py
tobe_time_mcp_11-0.1.4.dist-info/METADATA
tobe_time_mcp_11-0.1.4.dist-info/WHEEL
tobe_time_mcp_11-0.1.4.dist-info/entry_points.txt
tobe_time_mcp_11-0.1.4.dist-info/top_level.txt
tobe_time_mcp_11-0.1.4.dist-info/RECORD
