Metadata-Version: 2.4
Name: tobe_time_mcp_11
Version: 0.1.4
Summary: Add your description here
Requires-Python: >=3.12
Requires-Dist: fastmcp>=2.13.0.2
